json2tb/__init__.py
json2tb/main.py
json2tb-0.0.4.dist-info/METADATA
json2tb-0.0.4.dist-info/RECORD
json2tb-0.0.4.dist-info/WHEEL
json2tb-0.0.4.dist-info/entry_points.txt
json2tb-0.0.4.dist-info/top_level.txt
